prometheous/__init__.py
prometheous/cli.py
prometheous/core.py
prometheous/data/build_website.py
prometheous/data/cache_db_context.py
prometheous/data/code_view_demo.py
prometheous/data/codepiece_summarizer.py
prometheous/data/custom_doc_writer.py
prometheous/data/ensure_fdignore_with_doc.py
prometheous/data/estimate_utils.py
prometheous/data/example.py
prometheous/data/identify_utils.py
prometheous/data/llm.py
prometheous/data/path_select_utils.py
prometheous/data/recursive_document_writer.py
prometheous/data/slice_utils.py
prometheous/data/code_view_with_path_argument_and_anchor/code_view_demo.py
prometheous/data/demo_document_repository/src/identify_utils.py
prometheous/data/demo_document_repository/src/main.py
prometheous/data/demo_document_repository/src/test.py
prometheous/data/demo_document_repository/src/folder1/file.py
prometheous/data/demo_document_repository/src/folder1/folder2/file2.py
prometheous/data/serverless_document_template/src/identify_utils.py
prometheous/data/serverless_document_template/src/test.py
prometheous/data/sitemap_generator/main.py
prometheous/data/stdout_redirect_progress/main.py
prometheous/data/stdout_redirect_progress/main_once.py
prometheous/data/stdout_redirect_progress/main_once_char_by_char.py
prometheous/data/stdout_redirect_progress/test.py
prometheous/data/stdout_redirect_progress/test_no_patch.py
prometheous/data/title_generator/main.py
prometheous/data/tree_markdown_view_folder_hierarchy/high_level.py
prometheous/data/tree_markdown_view_folder_hierarchy/main.py
prometheous/data/tree_markdown_view_folder_hierarchy/main_recursive.py
prometheous/data/vectorstore_embedding_chat_rag/chat.py
prometheous/data/vectorstore_embedding_chat_rag/docarray_test.py
prometheous/data/vectorstore_embedding_chat_rag/llamaindex_test.py
prometheous/data/vectorstore_embedding_chat_rag/llamaindex_vector.py
prometheous/data/vectorstore_embedding_chat_rag/main.py
prometheous/data/vectorstore_embedding_chat_rag/prompts.py
prometheous-0.1.0.dist-info/licenses/LICENSE
prometheous-0.1.0.dist-info/METADATA
prometheous-0.1.0.dist-info/WHEEL
prometheous-0.1.0.dist-info/entry_points.txt
prometheous-0.1.0.dist-info/top_level.txt
prometheous-0.1.0.dist-info/RECORD
