Metadata-Version: 2.4
Name: prometheous
Version: 0.1.0
Summary: AI-powered documentation generation and vector indexing tool
Home-page: https://github.com/James4Ever0/prometheous
Author: James Brown
Author-email: James Brown <james@example.com>
License: MIT
Project-URL: Homepage, https://github.com/James4Ever0/prometheous
Project-URL: Repository, https://github.com/James4Ever0/prometheous
Project-URL: Issues, https://github.com/James4Ever0/prometheous/issues
Keywords: documentation,ai,vector-search,code-analysis
Classifier: Development Status :: 3 - Alpha
Classifier: Intended Audience :: Developers
Classifier: License :: OSI Approved :: MIT License
Classifier: Operating System :: OS Independent
Classifier: Programming Language :: Python :: 3
Classifier: Programming Language :: Python :: 3.8
Classifier: Programming Language :: Python :: 3.9
Classifier: Programming Language :: Python :: 3.10
Classifier: Programming Language :: Python :: 3.11
Classifier: Topic :: Software Development :: Documentation
Classifier: Topic :: Text Processing :: Indexing
Requires-Python: >=3.8
License-File: LICENSE
Requires-Dist: beartype
Requires-Dist: progressbar2
Requires-Dist: jinja2
Requires-Dist: langchain
Requires-Dist: parse
Requires-Dist: pydantic
Requires-Dist: tiktoken
Requires-Dist: tinydb
Requires-Dist: textual
Requires-Dist: markdown
Requires-Dist: humanize
Requires-Dist: rich
Requires-Dist: aiofiles
Requires-Dist: numpy
Requires-Dist: identify
Requires-Dist: openai
Requires-Dist: litellm
Requires-Dist: click>=8.0.0
Requires-Dist: langchain-ollama
Requires-Dist: docarray[hnswlib,proto]
Requires-Dist: llama_index
Dynamic: author
Dynamic: home-page
Dynamic: license-file
Dynamic: requires-python
